LICENSE
MANIFEST.in
README.md
pytest_inomaly.py
setup.py
pytest_Inomaly.egg-info/PKG-INFO
pytest_Inomaly.egg-info/SOURCES.txt
pytest_Inomaly.egg-info/dependency_links.txt
pytest_Inomaly.egg-info/entry_points.txt
pytest_Inomaly.egg-info/requires.txt
pytest_Inomaly.egg-info/top_level.txt